sondehub/__init__.py
sondehub/__main__.py
sondehub/amateur.py
sondehub-0.3.1.dist-info/entry_points.txt
sondehub-0.3.1.dist-info/LICENSE
sondehub-0.3.1.dist-info/WHEEL
sondehub-0.3.1.dist-info/METADATA
sondehub-0.3.1.dist-info/RECORD
