Metadata-Version: 2.1
Name: sondehub
Version: 0.3.1
Summary: SDK to access SondeHub open data, and helpers for uploading telemetry.
Home-page: https://github.com/projecthorus/pysondehub
License: GPL-3.0-or-later
Author: Michaela
Author-email: git@michaela.lgbt
Requires-Python: >=3.6,<4.0
Classifier: License :: OSI Approved :: GNU General Public License v3 or later (GPLv3+)
Classifier: Programming Language :: Python :: 3
Classifier: Programming Language :: Python :: 3.10
Classifier: Programming Language :: Python :: 3.6
Classifier: Programming Language :: Python :: 3.7
Classifier: Programming Language :: Python :: 3.8
Classifier: Programming Language :: Python :: 3.9
Requires-Dist: boto3 (>=1.14.44,<2.0.0)
Requires-Dist: paho-mqtt (>=1.5.1,<2.0.0)
Requires-Dist: python-dateutil (>=2.8,<3.0)
Requires-Dist: requests (>=2.24.0,<3.0.0)
Project-URL: Documentation, https://github.com/projecthorus/pysondehub
Project-URL: Repository, https://github.com/projecthorus/pysondehub.git
